d3p/__init__.py
d3p/dputil.py
d3p/gmm.py
d3p/minibatch.py
d3p/modelling.py
d3p/optimizers.py
d3p/svi.py
d3p/util.py
d3p/version.py
d3p/random/__init__.py
d3p/random/debug.py
d3p-0.2.0.dist-info/METADATA
d3p-0.2.0.dist-info/WHEEL
d3p-0.2.0.dist-info/top_level.txt
d3p-0.2.0.dist-info/RECORD
