Metadata-Version: 2.1
Name: d3p
Version: 0.2.0
Summary: Differentially-Private Probabilistic Programming using NumPyro and the differentially-private variational inference algorithm
Author: FCAI R4 @ Helsinki University and Aalto University
Keywords: probabilistic machine learning bayesian statistics differential-privacy
Classifier: Intended Audience :: Developers
Classifier: Intended Audience :: Education
Classifier: Intended Audience :: Science/Research
Classifier: Operating System :: POSIX :: Linux
Classifier: Operating System :: MacOS :: MacOS X
Classifier: Programming Language :: Python :: 3
Requires-Python: >=3.7
Requires-Dist: numpyro[cpu] (<2.0.0,>=0.8.0)
Requires-Dist: jax (>=0.2.20)
Requires-Dist: fourier-accountant (<1.0.0,>=0.12.0)
Requires-Dist: jax-chacha-prng (<2,>=1)
Provides-Extra: compatible-dependencies
Requires-Dist: numpyro (==0.10.1) ; extra == 'compatible-dependencies'
Requires-Dist: jax[cpu] (==0.3.23) ; extra == 'compatible-dependencies'
Provides-Extra: cpu
Provides-Extra: cuda
Requires-Dist: numpyro[cuda] ; extra == 'cuda'
Provides-Extra: examples
Requires-Dist: matplotlib ; extra == 'examples'
Provides-Extra: tpu
Requires-Dist: numpyro[tpu] ; extra == 'tpu'
